OpenFisca_US-0.124.1.data/data/share/openfisca/openfisca-country-template/CHANGELOG.md
OpenFisca_US-0.124.1.data/data/share/openfisca/openfisca-country-template/LICENSE
OpenFisca_US-0.124.1.data/data/share/openfisca/openfisca-country-template/README.md
openfisca_us/__init__.py
openfisca_us/entities.py
openfisca_us/model_api.py
openfisca_us/system.py
openfisca_us/typing.py
openfisca_us/api/__init__.py
openfisca_us/api/hypothetical.py
openfisca_us/api/microsimulation.py
openfisca_us/data/__init__.py
openfisca_us/data/cli.py
openfisca_us/data/datasets/__init__.py
openfisca_us/data/datasets/acs/__init__.py
openfisca_us/data/datasets/acs/acs.py
openfisca_us/data/datasets/acs/raw_acs.py
openfisca_us/data/datasets/cps/README.md
openfisca_us/data/datasets/cps/__init__.py
openfisca_us/data/datasets/cps/cps.py
openfisca_us/data/datasets/cps/raw_cps.py
openfisca_us/data/geography/README.md
openfisca_us/data/geography/create_zip_code_dataset.py
openfisca_us/data/geography/zip_codes.csv.gz
openfisca_us/data/parameters/README.md
openfisca_us/data/parameters/gov/hhs/medicaid/geography/medicaid_rating_area.yaml
openfisca_us/data/parameters/gov/hhs/medicaid/geography/second_lowest_silver_plan_cost.yaml
openfisca_us/data/storage/README.md
openfisca_us/data/storage/__init__.py
openfisca_us/parameters/__init__.py
openfisca_us/parameters/calibration/populations/by_state.yaml
openfisca_us/parameters/calibration/programs/income/dividends/qualified_percentage.yaml
openfisca_us/parameters/calibration/programs/medicaid/budgetary_impact.yaml
openfisca_us/parameters/calibration/programs/medicaid/enrollment.yaml
openfisca_us/parameters/calibration/programs/snap/budgetary_impact.yaml
openfisca_us/parameters/calibration/programs/snap/caseload.yaml
openfisca_us/parameters/contrib/congress/senate/democrats/inflation_reduction_act/in_effect.yaml
openfisca_us/parameters/contrib/congress/senate/democrats/inflation_reduction_act/electric_vehicle_credit/new/battery_components/amount.yaml
OpenFisca_US-0.124.1.dist-info/LICENSE
OpenFisca_US-0.124.1.dist-info/METADATA
OpenFisca_US-0.124.1.dist-info/WHEEL
OpenFisca_US-0.124.1.dist-info/entry_points.txt
OpenFisca_US-0.124.1.dist-info/top_level.txt
OpenFisca_US-0.124.1.dist-info/RECORD
