Metadata-Version: 2.1
Name: OpenFisca-US
Version: 0.124.1
Summary: OpenFisca tax and benefit system for the US
Home-page: https://github.com/PolicyEngine/openfisca-us
Author: PolicyEngine
Author-email: hello@policyengine.org
License: http://www.fsf.org/licensing/licenses/agpl-3.0.html
Keywords: benefit microsimulation social tax
Platform: UNKNOWN
Classifier: Development Status :: 5 - Production/Stable
Classifier: License :: OSI Approved :: GNU Affero General Public License v3
Classifier: Operating System :: POSIX
Classifier: Programming Language :: Python
Classifier: Programming Language :: Python :: 3.7
Classifier: Topic :: Scientific/Engineering :: Information Analysis
Requires-Python: >=3.7,<3.8
Requires-Dist: h5py
Requires-Dist: microdf-python
Requires-Dist: OpenFisca-Core[web-api] (>=35.0.0)
Requires-Dist: OpenFisca-Tools (<1.0.0,>=0.13.3)
Requires-Dist: pandas
Requires-Dist: pathlib
Requires-Dist: pytest
Requires-Dist: pytest-dependency
Requires-Dist: pyyaml
Requires-Dist: requests
Requires-Dist: synthimpute
Requires-Dist: tables
Requires-Dist: tqdm
Requires-Dist: click (>=8.0.0)
Provides-Extra: dev
Requires-Dist: autopep8 (<2.0.0,>=1.5.4) ; extra == 'dev'
Requires-Dist: black ; extra == 'dev'
Requires-Dist: coverage ; extra == 'dev'
Requires-Dist: jupyter-book ; extra == 'dev'
Requires-Dist: plotly ; extra == 'dev'
Requires-Dist: pytest ; extra == 'dev'
Requires-Dist: setuptools ; extra == 'dev'
Requires-Dist: wheel ; extra == 'dev'
Requires-Dist: yaml-changelog (>=0.1.7) ; extra == 'dev'
Requires-Dist: linecheck ; extra == 'dev'
